Metadata-Version: 1.1
Name: qacode
Version: 0.6.4
Summary: Main automation library to wrap selenium and automate webs
Home-page: https://github.com/netzulo/qacode
Author: Netzulo Open Source
Author-email: netzuleando@gmail.com
License: ﻿                    GNU GENERAL PUBLIC LICENSE
